pysl4land/__init__.py
pysl4land/pysl4land_gedi.py
pysl4land/pysl4land_icesat2.py
pysl4land/pysl4land_utils.py
pysl4land-0.1.0.data/scripts/pysl4landgeditools.py
pysl4land-0.1.0.data/scripts/pysl4landicesat2tools.py
pysl4land-0.1.0.dist-info/LICENSE
pysl4land-0.1.0.dist-info/METADATA
pysl4land-0.1.0.dist-info/WHEEL
pysl4land-0.1.0.dist-info/top_level.txt
pysl4land-0.1.0.dist-info/RECORD
